skill/__init__.py
skill-0.0.7.dist-info/LICENSE
skill-0.0.7.dist-info/METADATA
skill-0.0.7.dist-info/WHEEL
skill-0.0.7.dist-info/top_level.txt
skill-0.0.7.dist-info/RECORD
