Metadata-Version: 2.1
Name: skill
Version: 0.0.7
Summary: Extract code exercises from code itself
Home-page: https://github.com/thorwhalen/skill
Author: Thor Whalen
License: mit
Platform: any
License-File: LICENSE
